HadiDB/__init__.py
HadiDB/auth.py
HadiDB/config.py
HadiDB/count.py
HadiDB/countbyAll.py
HadiDB/createDB.py
HadiDB/delete.py
HadiDB/delete_collection.py
HadiDB/delete_database.py
HadiDB/engine.py
HadiDB/get_all_data.py
HadiDB/get_schema.py
HadiDB/getbyID.py
HadiDB/getbyKey.py
HadiDB/getbyKeys.py
HadiDB/haditechnique.py
HadiDB/hash.py
HadiDB/insert.py
HadiDB/operation.py
HadiDB/paths.py
HadiDB/schema.py
HadiDB/update.py
HadiDB/write.py
HadiDB-0.1.dist-info/METADATA
HadiDB-0.1.dist-info/WHEEL
HadiDB-0.1.dist-info/top_level.txt
HadiDB-0.1.dist-info/RECORD
