Metadata-Version: 2.1
Name: HadiDB
Version: 0.1
Summary: HadiDB is a lightweight, extremely horizontally scalable database written in Python.
Author: mominiqbal1234
Author-email: <mominiqbal1214@gmail.com>
Keywords: python,pyjsondbpython database,hadidb,python hadidb,hadidb django
Classifier: Development Status :: 1 - Planning
Classifier: Intended Audience :: Developers
Classifier: Programming Language :: Python :: 3
Classifier: Operating System :: Unix
Classifier: Operating System :: MacOS :: MacOS X
Classifier: Operating System :: Microsoft :: Windows
Requires-Dist: filelock
